{
  "/": {
    "src/shared/components/home-page.js": {
      "type": "script",
      "weight": 1
    },
    "node_modules/@webcomponents/webcomponentsjs/webcomponents-loader.js": {
      "type": "script",
      "weight": 1
    }
  },
  "/home": {
    "src/app.js": {
      "type": "script",
      "weight": 1
    },
    "src/shared/components/home.js": {
      "type": "script",
      "weight": 1
    },
    "node_modules/@webcomponents/webcomponentsjs/webcomponents-loader.js": {
      "type": "script",
      "weight": 1
    }
  }
}
